league_of_legends_ml/__init__.py
league_of_legends_ml/common/__init__.py
league_of_legends_ml/grade/__init__.py
league_of_legends_ml/mastery/__init__.py
league_of_legends_ml/mastery/files/__init__.py
league_of_legends_ml/mastery/files/aram_ensemble_model.pkl
league_of_legends_ml/mastery/files/aram_ensemble_scaler.pkl
league_of_legends_ml/mastery/files/aram_model.pkl
league_of_legends_ml/mastery/files/aram_scaler.pkl
league_of_legends_ml/mastery/files/classic_ensemble_model.pkl
league_of_legends_ml/mastery/files/classic_ensemble_scaler.pkl
league_of_legends_ml/mastery/files/classic_model.pkl
league_of_legends_ml/mastery/files/classic_scaler.pkl
league_of_legends_ml/mastery/files/model.pkl
league_of_legends_ml/mastery/files/scaler.pkl
league_of_legends_ml-0.0.9.dist-info/METADATA
league_of_legends_ml-0.0.9.dist-info/WHEEL
league_of_legends_ml-0.0.9.dist-info/top_level.txt
league_of_legends_ml-0.0.9.dist-info/RECORD
